FamaFrenchDownloader/__init__.py
FamaFrenchDownloader/downloader.py
famafrenchdownloader-0.1.1.dist-info/METADATA
famafrenchdownloader-0.1.1.dist-info/WHEEL
famafrenchdownloader-0.1.1.dist-info/top_level.txt
famafrenchdownloader-0.1.1.dist-info/RECORD
